apitist/__init__.py
apitist/apitist.py
apitist/constructor.py
apitist/decorators.py
apitist/hooks.py
apitist/logging.py
apitist/random.py
apitist/requests.py
apitist/requests.pyi
apitist/utils.py
apitist-4.3.0.dist-info/AUTHORS.rst
apitist-4.3.0.dist-info/LICENSE.txt
apitist-4.3.0.dist-info/METADATA
apitist-4.3.0.dist-info/WHEEL
apitist-4.3.0.dist-info/top_level.txt
apitist-4.3.0.dist-info/RECORD
