Metadata-Version: 2.1
Name: apitist
Version: 4.3.0
Summary: Brand new way to test your API
Home-page: https://github.com/zeburek/python-apitist
Author: Parviz Khavari
Author-email: csctclan@gmail.com
License: gpl3
Platform: any
Classifier: Development Status :: 4 - Beta
Classifier: Intended Audience :: Developers
Classifier: License :: OSI Approved :: GNU General Public License v3 (GPLv3)
Classifier: Programming Language :: Python
Classifier: Programming Language :: Python :: 3.7
Classifier: Programming Language :: Python :: 3.8
Classifier: Programming Language :: Python :: 3.9
Classifier: Topic :: Software Development :: Quality Assurance
Classifier: Topic :: Software Development :: Testing
Classifier: Typing :: Typed
Requires-Python: >=3.7
Provides-Extra: random
Provides-Extra: testing
Provides-Extra: dev
